controllers/__init__.py
controllers/clientes_controller.py
controllers/facturacion_controller.py
controllers/servicios_controller.py
controllers/tratamientos_controller.py
models/__init__.py
models/cliente.py
models/factura.py
models/servicio.py
models/tratamiento.py
utils/D&G.png
utils/__init__.py
utils/file_manager.py
utils/styles.py
utils/validators.py
views/__init__.py
views/clientes_view.py
views/configuracion_empresa_view.py
views/estadisticas_diarias_view.py
views/estadisticas_view.py
views/main_window.py
views/servicios_view.py
views/trimestral_view.py
esteticapeluqueria-1.0.0.dist-info/METADATA
esteticapeluqueria-1.0.0.dist-info/WHEEL
esteticapeluqueria-1.0.0.dist-info/entry_points.txt
esteticapeluqueria-1.0.0.dist-info/top_level.txt
esteticapeluqueria-1.0.0.dist-info/RECORD
